{
    "team-name": "To-Lose Weight",
    "league-name": "Copr",
    "players": [
        {
            "name": "Matthew Miles",
            "age": "blank",
            "isCaptain": false,
            "isViceCaptain": false,
            "isActive": true,
            "isPrivate": false,
            "isHero": false,
            "isTOTW": false,
            "profile": {
                "hometown": "",
                "career": "",
                "hobbies": "",
                "favouriteFood": "",
                "favouriteTeam": "",
                "joiningReason": ""
            },
            "pitch": {
                "position": "Defence",
                "matchesPlayed": "0",
                "goals": "0",
                "elevensTeam": "None",
                "favouriteTeamMate": "",
                "hatePlayingAgainst": ""
            }
        },
        {
            "name": "Ben Williams",
            "age": "blank",
            "isCaptain": false,
            "isViceCaptain": false,
            "isActive": true,
            "isPrivate": false,
            "isHero": false,
            "isTOTW": false,
            "profile": {
                "hometown": "",
                "career": "",
                "hobbies": "",
                "favouriteFood": "",
                "favouriteTeam": "",
                "joiningReason": ""
            },
            "pitch": {
                "position": "Defence",
                "matchesPlayed": "0",
                "goals": "0",
                "elevensTeam": "None",
                "favouriteTeamMate": "",
                "hatePlayingAgainst": ""
            }
        },
        {
            "name": "Chris Simmons",
            "age": "blank",
            "isCaptain": false,
            "isViceCaptain": false,
            "isActive": true,
            "isPrivate": false,
            "isHero": false,
            "isTOTW": false,
            "profile": {
                "hometown": "",
                "career": "",
                "hobbies": "",
                "favouriteFood": "",
                "favouriteTeam": "",
                "joiningReason": ""
            },
            "pitch": {
                "position": "Defence",
                "matchesPlayed": "0",
                "goals": "0",
                "elevensTeam": "None",
                "favouriteTeamMate": "",
                "hatePlayingAgainst": ""
            }
        },
        {
            "name": "Craig Evans",
            "age": "blank",
            "isCaptain": false,
            "isViceCaptain": true,
            "isActive": true,
            "isPrivate": false,
            "isHero": false,
            "isTOTW": false,
            "profile": {
                "hometown": "",
                "career": "",
                "hobbies": "",
                "favouriteFood": "",
                "favouriteTeam": "",
                "joiningReason": ""
            },
            "pitch": {
                "position": "Defence",
                "matchesPlayed": "0",
                "goals": "0",
                "elevensTeam": "None",
                "favouriteTeamMate": "",
                "hatePlayingAgainst": ""
            }
        },
        {
            "name": "Marc Lockwood",
            "age": "blank",
            "isCaptain": false,
            "isViceCaptain": false,
            "isActive": true,
            "isPrivate": false,
            "isHero": false,
            "isTOTW": false,
            "profile": {
                "hometown": "",
                "career": "",
                "hobbies": "",
                "favouriteFood": "",
                "favouriteTeam": "",
                "joiningReason": ""
            },
            "pitch": {
                "position": "Defence",
                "matchesPlayed": "0",
                "goals": "0",
                "elevensTeam": "None",
                "favouriteTeamMate": "",
                "hatePlayingAgainst": ""
            }
        },
        {
            "name": "Matthew Couch",
            "age": "blank",
            "isCaptain": false,
            "isViceCaptain": false,
            "isActive": true,
            "isPrivate": false,
            "isHero": false,
            "isTOTW": false,
            "profile": {
                "hometown": "",
                "career": "",
                "hobbies": "",
                "favouriteFood": "",
                "favouriteTeam": "",
                "joiningReason": ""
            },
            "pitch": {
                "position": "Defence",
                "matchesPlayed": "0",
                "goals": "0",
                "elevensTeam": "None",
                "favouriteTeamMate": "",
                "hatePlayingAgainst": ""
            }
        },
        {
            "name": "Owen Llewellyn",
            "age": "blank",
            "isCaptain": false,
            "isViceCaptain": false,
            "isActive": true,
            "isPrivate": false,
            "isHero": false,
            "isTOTW": false,
            "profile": {
                "hometown": "",
                "career": "",
                "hobbies": "",
                "favouriteFood": "",
                "favouriteTeam": "",
                "joiningReason": ""
            },
            "pitch": {
                "position": "Defence",
                "matchesPlayed": "0",
                "goals": "0",
                "elevensTeam": "None",
                "favouriteTeamMate": "",
                "hatePlayingAgainst": ""
            }
        },
        {
            "name": "Ryan Hawkins",
            "age": "27",
            "isCaptain": false,
            "isViceCaptain": false,
            "isActive": true,
            "isPrivate": false,
            "isHero": false,
            "isTOTW": false,
            "profile": {
                "hometown": "Swansea",
                "career": "Mitie Supervisor",
                "hobbies": "Football",
                "favouriteFood": "Steak,chips, peppcorn sauce",
                "favouriteTeam": "Swansea",
                "joiningReason": "Healthier lifestyle and to get fitter"
            },
            "pitch": {
                "position": "Midfield",
                "matchesPlayed": "0",
                "goals": "0",
                "elevensTeam": "None",
                "favouriteTeamMate": "TG & Craig Evans",
                "hatePlayingAgainst": "Anyone who kicks me 😂"
            }
        },
        {
            "name": "Simon Gear",
            "age": "blank",
            "isCaptain": true,
            "isViceCaptain": false,
            "isActive": true,
            "isPrivate": false,
            "isHero": false,
            "isTOTW": false,
            "profile": {
                "hometown": "",
                "career": "",
                "hobbies": "",
                "favouriteFood": "",
                "favouriteTeam": "",
                "joiningReason": ""
            },
            "pitch": {
                "position": "Defence",
                "matchesPlayed": "0",
                "goals": "0",
                "elevensTeam": "None",
                "favouriteTeamMate": "",
                "hatePlayingAgainst": ""
            }
        },
        {
            "name": "",
            "age": "blank",
            "isCaptain": false,
            "isViceCaptain": false,
            "isActive": true,
            "isPrivate": false,
            "isHero": false,
            "isTOTW": false,
            "profile": {
                "hometown": "",
                "career": "",
                "hobbies": "",
                "favouriteFood": "",
                "favouriteTeam": "",
                "joiningReason": ""
            },
            "pitch": {
                "position": "Defence",
                "matchesPlayed": "0",
                "goals": "0",
                "elevensTeam": "None",
                "favouriteTeamMate": "",
                "hatePlayingAgainst": ""
            }
        },
        {
            "name": "",
            "age": "blank",
            "isCaptain": false,
            "isViceCaptain": false,
            "isActive": true,
            "isPrivate": false,
            "isHero": false,
            "isTOTW": false,
            "profile": {
                "hometown": "",
                "career": "",
                "hobbies": "",
                "favouriteFood": "",
                "favouriteTeam": "",
                "joiningReason": ""
            },
            "pitch": {
                "position": "Defence",
                "matchesPlayed": "0",
                "goals": "0",
                "elevensTeam": "None",
                "favouriteTeamMate": "",
                "hatePlayingAgainst": ""
            }
        }
    ]
}